homo_py/__init__.py
homo_py/homo.py
homo_py/statics/nums.json
homo_py/utils.py
python_homo_generator-1.1.0.dist-info/LICENSE
python_homo_generator-1.1.0.dist-info/METADATA
python_homo_generator-1.1.0.dist-info/WHEEL
python_homo_generator-1.1.0.dist-info/RECORD
