Metadata-Version: 2.1
Name: python-homo-generator
Version: 1.1.0
Summary: A tool that breaks down any number into a formula consisting of 114514. Make by python
Home-page: https://github.com/miyago9267/homo-py
License: MIT
Keywords: symbolic,decomposition,numbers,homo
Author: miyago9267
Author-email: miyagomizugen@gmail.com
Requires-Python: >=3.12,<4.0
Classifier: License :: OSI Approved :: MIT License
Classifier: Programming Language :: Python :: 3
Classifier: Programming Language :: Python :: 3.12
Classifier: Programming Language :: Python :: 3.13
Project-URL: Repository, https://github.com/miyago9267/homo-py
